README.md
setup.py
src/repair_spec.egg-info/PKG-INFO
src/repair_spec.egg-info/SOURCES.txt
src/repair_spec.egg-info/dependency_links.txt
src/repair_spec.egg-info/requires.txt
src/repair_spec.egg-info/top_level.txt
src/specrepair/__init__.py
src/specrepair/bot.py
src/specrepair/utils.py