Metadata-Version: 2.1
Name: repair-spec
Version: 0.1.0.dev3
Summary: Auto repair spec
Home-page: https://github.com/zhangsibo1129/specrepair
Author: Sibo Zhang
Author-email: zhangsibo1129@gmail.com
Classifier: Programming Language :: Python :: 3
Classifier: License :: OSI Approved :: MIT License
Classifier: Operating System :: OS Independent
Requires-Python: >=3.8
Requires-Dist: openai
